  [{"id":"933","videoID":"zlf_S4P47oI","videosName":"Deutsch lernen: Aussprache von R im Deutschen\/German pronunciation of R (learn German)","videoDuration":"00:02:15","getFromList":"PLU6oUZlKAyKtswWw___P7wt2ZpXQeVyfN","categoryID":"0"},{"id":"934","videoID":"2Q6W8OgnE3M","videosName":"Deutsch lernen: Aussprache von -ig und -ich am Wortende\/German: pronunciation of -ig & -ich","videoDuration":"00:01:52","getFromList":"PLU6oUZlKAyKtswWw___P7wt2ZpXQeVyfN","categoryID":"0"},{"id":"935","videoID":"OsR9j79IDVw","videosName":"Challenge Deutsch lernen (Tag 7): R oder kein ER - Wie spreche ich es aus?","videoDuration":"00:21:36","getFromList":"PLU6oUZlKAyKtswWw___P7wt2ZpXQeVyfN","categoryID":"0"},{"id":"936","videoID":"M3uqlfoU50c","videosName":"Deutsch: Aussprache von CH (deutsche Untertitel)\/Pronunciation of CH (German subtitles)","videoDuration":"00:07:13","getFromList":"PLU6oUZlKAyKtswWw___P7wt2ZpXQeVyfN","categoryID":"0"},{"id":"937","videoID":"OpDt69-qz8I","videosName":"Deutsch lernen: Aussprache von CH in \u201eich\" im Deutschen\/German pronunciation of CH (learn German)","videoDuration":"00:01:20","getFromList":"PLU6oUZlKAyKtswWw___P7wt2ZpXQeVyfN","categoryID":"0"},{"id":"938","videoID":"6XEh95THRMk","videosName":"\u041a\u0430\u043a \u043f\u0440\u043e\u0438\u0437\u043d\u043e\u0441\u0438\u0442\u0441\u044f \u041d\u0435\u043c\u0435\u0446\u043a\u043e\u0435 R \/ \u0418\u0440\u0438\u043d\u0430 \u0428\u0418","videoDuration":"00:03:50","getFromList":"PLU6oUZlKAyKtswWw___P7wt2ZpXQeVyfN","categoryID":"0"}]